[
  {
    "id": "inbound_cs_01",
    "title": "Inbound Customer Service",
    "category": "Customer Service",
    "industry": "General",
    "filePath": "@assets/inbound_cs_01.wav",
    "language": "en-US",
    "voiceProfile": "Female, neutral, professional",
    "description": "AI agent answers an incoming customer call, verifies identity, answers FAQ and takes message of customer needs."
  },
  {
    "id": "new_client_appointment_01",
    "title": "New Client Appointment",
    "category": "Appointment Scheduling",
    "industry": "General",
    "filePath": "@assets/new_client_appointment_01.wav",
    "language": "en-US",
    "voiceProfile": "Male, friendly, upbeat",
    "description": "AI agent books appointments for new or existing clients. The agent can take inbound calls, or place outbound calls to get appointments scheduled."
  },
  {
    "id": "lead_followup_01",
    "title": "Lead Follow-Up",
    "category": "Sales / Outbound",
    "industry": "General",
    "filePath": "",
    "language": "en-US",
    "voiceProfile": "Female, confident",
    "description": "AI agent follows up with a new lead, answers basic questions, and books a call or appointment with your team."
  },
  {
    "id": "estimate_outreach_01",
    "title": "Estimate Outreach",
    "category": "Sales / Outbound",
    "industry": "General",
    "filePath": "",
    "language": "en-US",
    "voiceProfile": "Male, friendly, professional",
    "description": "AI agent reaches out regarding a service inquiry, provides basic information, and schedules an estimate or consultation."
  },
  {
    "id": "status_followup_01",
    "title": "Status Follow-Up",
    "category": "Follow-Up & Reminders",
    "industry": "General",
    "filePath": "",
    "language": "en-US",
    "voiceProfile": "Male, reassuring, clear",
    "description": "AI agent provides a status update on an ongoing request and answers common questions so customers stay informed."
  }
]
